<?xml version='1.0' encoding ='UTF-8' ?>
<!DOCTYPE suite SYSTEM "http://testng.org/testng-1.0.dtd">
<suite name="Draft Post Suite" verbose="1" >
<parameter name = "posttitle" value = "Normal Post"></parameter>
  
 <test name="Method TC2" >
    <classes>
       <class name="Admin.DashBoard_Draft_And_Repost">
        <methods>
               <include name="openPublishDraft" />
        
      
     </methods>
       </class>
    </classes>
  </test>  
 
  <test name="Method TC1" >
    <classes>
       <class name="Admin.CreatePostExcel">
          </class>
    </classes>
  </test> 
   <test name="Method TC1" >
    <classes>
       <class name="Admin.CreatePostExcel">
          </class>
    </classes>
  </test> 
 <parameter name = "posttitleDraft" value = "Normal Post"></parameter>
  
 <test name="Method TC2" >
    <classes>
       <class name="Admin.DashBoard_Draft_And_Repost">
        <methods>
               <include name="openPublishdraft2" />
        
      
     </methods>
       </class>
    </classes>
  </test> 
</suite>
